pullenti_client/__init__.py
pullenti_client/client.py
pullenti_client/compat.py
pullenti_client/flat.py
pullenti_client/graph.py
pullenti_client/referent.py
pullenti_client/result.py
pullenti_client/utils.py
pullenti_client-0.6.0.dist-info/METADATA
pullenti_client-0.6.0.dist-info/WHEEL
pullenti_client-0.6.0.dist-info/top_level.txt
pullenti_client-0.6.0.dist-info/RECORD
